CHANGES.txt
DESC.txt
LICENSE.txt
MANIFEST.in
README.md
setup.py
FormatBlock.egg-info/PKG-INFO
FormatBlock.egg-info/SOURCES.txt
FormatBlock.egg-info/dependency_links.txt
FormatBlock.egg-info/entry_points.txt
FormatBlock.egg-info/requires.txt
FormatBlock.egg-info/top_level.txt
docs/mit.txt
fmtblock/__init__.py
fmtblock/__main__.py
fmtblock/escapecodes.py
fmtblock/formatters.py
test/__init__.py
test/test_fmtblock.py