Metadata-Version: 1.1
Name: FormatBlock
Version: 0.4.1
Summary: Format blocks of characters for display, split by words, characters, or newlines.
